jquantsapi/__init__.py
jquantsapi/apis/__init__.py
jquantsapi/apis/base.py
jquantsapi/apis/v1/__init__.py
jquantsapi/apis/v1/derivatives.py
jquantsapi/apis/v1/fins.py
jquantsapi/apis/v1/indices.py
jquantsapi/apis/v1/listed.py
jquantsapi/apis/v1/markets.py
jquantsapi/apis/v1/prices.py
jquantsapi/apis/v2/__init__.py
jquantsapi/apis/v2/bulk.py
jquantsapi/apis/v2/derivatives.py
jquantsapi/apis/v2/equities.py
jquantsapi/apis/v2/fins.py
jquantsapi/apis/v2/indices.py
jquantsapi/apis/v2/markets.py
jquantsapi/client.py
jquantsapi/client_v2.py
jquantsapi/constants.py
jquantsapi/enums.py
jquants_api_client-2.0.0.dist-info/METADATA
jquants_api_client-2.0.0.dist-info/WHEEL
jquants_api_client-2.0.0.dist-info/licenses/LICENSE
jquants_api_client-2.0.0.dist-info/RECORD
