Metadata-Version: 2.4
Name: jquants-api-client
Version: 2.0.0
Summary: J-Quants API Client Library
License: Apache-2.0
License-File: LICENSE
Keywords: jquants,api,client,J-Quants
Author: J-Quants Project Contributors
Author-email: j-quants@jpx.co.jp
Requires-Python: >=3.10,<4.0
Classifier: License :: OSI Approved :: Apache Software License
Classifier: Operating System :: OS Independent
Classifier: Programming Language :: Python :: 3
Classifier: Programming Language :: Python :: 3.10
Classifier: Programming Language :: Python :: 3.11
Classifier: Programming Language :: Python :: 3.12
Classifier: Programming Language :: Python :: 3.13
Classifier: Programming Language :: Python :: 3.14
Requires-Dist: numpy (>=1.22.4)
Requires-Dist: pandas (>=2.2.0,<3.0.0)
Requires-Dist: requests (>=2.28.0,<3.0.0)
Requires-Dist: tenacity (>=8.2.0,<9.0.0)
Requires-Dist: tomli (>=2.0.1,<3.0.0) ; python_version < "3.11"
Requires-Dist: typing_extensions (>=4.5.0,<5.0.0) ; python_version < "3.13"
Project-URL: Bug Tracker, https://github.com/J-Quants/jquants-api-client-python/issues
Project-URL: Homepage, https://github.com/J-Quants/jquants-api-client-python
